{
  "meta": {
    "timestamp": "2025-08-22T20:47:18.431420",
    "shots": 20000,
    "seed": 42,
    "backends": [
      "aer_simulator"
    ],
    "p0": 0.25,
    "target_states": [
      "0000",
      "0001",
      "0010",
      "0011"
    ],
    "total_executions": 1
  },
  "results": [
    {
      "backend": "aer_simulator",
      "circuit_index": 0,
      "counts": {
        "0000": 5049,
        "0010": 4968,
        "0001": 5012,
        "0011": 4971
      },
      "summary": {
        "total_shots": 20000,
        "success_counts": 20000,
        "p_obs": 1.0,
        "effect_size": 2.0943951023931953
      },
      "stats": {
        "z": 244.94897427831782,
        "p_value": 0.0,
        "ci95_low": 1.0,
        "ci95_high": 1.0,
        "standard_error": 0.0,
        "p_value_bonferroni_threshold": 0.05,
        "p_value_fdr_adj": 0.0
      },
      "execution_time": 0.07835197448730469
    }
  ]
}